ament_cmake_vendor_package/_dummy.cpython-313-x86_64-linux-gnu.so
ros_ament_cmake_vendor_package-2.7.3.data/data/share/ament_cmake_vendor_package/local_setup.bash
ros_ament_cmake_vendor_package-2.7.3.data/data/share/ament_cmake_vendor_package/local_setup.dsv
ros_ament_cmake_vendor_package-2.7.3.data/data/share/ament_cmake_vendor_package/local_setup.sh
ros_ament_cmake_vendor_package-2.7.3.data/data/share/ament_cmake_vendor_package/local_setup.zsh
ros_ament_cmake_vendor_package-2.7.3.data/data/share/ament_cmake_vendor_package/package.dsv
ros_ament_cmake_vendor_package-2.7.3.data/data/share/ament_cmake_vendor_package/package.xml
ros_ament_cmake_vendor_package-2.7.3.data/data/share/ament_cmake_vendor_package/cmake/ament_cmake_export_dependencies-extras.cmake
ros_ament_cmake_vendor_package-2.7.3.data/data/share/ament_cmake_vendor_package/cmake/ament_cmake_vendor_package-extras.cmake
ros_ament_cmake_vendor_package-2.7.3.data/data/share/ament_cmake_vendor_package/cmake/ament_cmake_vendor_packageConfig-version.cmake
ros_ament_cmake_vendor_package-2.7.3.data/data/share/ament_cmake_vendor_package/cmake/ament_cmake_vendor_packageConfig.cmake
ros_ament_cmake_vendor_package-2.7.3.data/data/share/ament_cmake_vendor_package/cmake/ament_vendor.cmake
ros_ament_cmake_vendor_package-2.7.3.data/data/share/ament_cmake_vendor_package/cmake/templates/target.repos.in
ros_ament_cmake_vendor_package-2.7.3.data/data/share/ament_cmake_vendor_package/cmake/templates/vendor_package.bat.in
ros_ament_cmake_vendor_package-2.7.3.data/data/share/ament_cmake_vendor_package/cmake/templates/vendor_package.dsv.in
ros_ament_cmake_vendor_package-2.7.3.data/data/share/ament_cmake_vendor_package/cmake/templates/vendor_package.sh.in
ros_ament_cmake_vendor_package-2.7.3.data/data/share/ament_cmake_vendor_package/cmake/templates/vendor_package_cmake_prefix.bat.in
ros_ament_cmake_vendor_package-2.7.3.dist-info/METADATA
ros_ament_cmake_vendor_package-2.7.3.dist-info/WHEEL
ros_ament_cmake_vendor_package-2.7.3.dist-info/top_level.txt
ros_ament_cmake_vendor_package-2.7.3.dist-info/RECORD
