Metadata-Version: 2.4
Name: ros-ament-cmake-vendor-package
Version: 2.7.3
Summary: Wheel for the ament_cmake_vendor_package (ros-ament-cmake-vendor-package) ROS 2 package.
Dynamic: description
Dynamic: description-content-type
Dynamic: summary
